pyqttoast/__init__.py
pyqttoast/constants.py
pyqttoast/drop_shadow.py
pyqttoast/icon_utils.py
pyqttoast/toast.py
pyqttoast/toast_enums.py
pyqttoast/utils.py
pyqttoast/css/drop_shadow.css
pyqttoast/css/toast.css
pyqttoast/hooks/__init__.py
pyqttoast/hooks/hook-pyqttoast.py
pyqttoast/icons/close.png
pyqttoast/icons/error.png
pyqttoast/icons/information.png
pyqttoast/icons/success.png
pyqttoast/icons/warning.png
pyqttoast_enhanced-2.0.0.dist-info/licenses/LICENSE
pyqttoast_enhanced-2.0.0.dist-info/METADATA
pyqttoast_enhanced-2.0.0.dist-info/WHEEL
pyqttoast_enhanced-2.0.0.dist-info/entry_points.txt
pyqttoast_enhanced-2.0.0.dist-info/top_level.txt
pyqttoast_enhanced-2.0.0.dist-info/RECORD
