Metadata-Version: 2.4
Name: pyqttoast-enhanced
Version: 2.0.0
Summary: Enhanced fork of pyqt-toast-notification with additional features and improvements
Home-page: https://github.com/Cassianvale/pyqttoast
Author: CassianVale
Author-email: CassianVale <z1430066373@gmail.com>
License-Expression: MIT
Project-URL: Homepage, https://github.com/Cassianvale/pyqttoast
Project-URL: Documentation, https://github.com/Cassianvale/pyqttoast/blob/main/README.md
Project-URL: Repository, https://github.com/Cassianvale/pyqttoast
Project-URL: Bug Reports, https://github.com/Cassianvale/pyqttoast/issues
Project-URL: Original Project, https://github.com/niklashenning/pyqttoast
Keywords: python,pyqt,qt,toast,notification,enhanced,fork
Classifier: Development Status :: 4 - Beta
Classifier: Intended Audience :: Developers
Classifier: Topic :: Software Development :: Libraries :: Python Modules
Classifier: Topic :: Software Development :: User Interfaces
Classifier: Programming Language :: Python :: 3
Classifier: Programming Language :: Python :: 3.7
Classifier: Programming Language :: Python :: 3.8
Classifier: Programming Language :: Python :: 3.9
Classifier: Programming Language :: Python :: 3.10
Classifier: Programming Language :: Python :: 3.11
Classifier: Programming Language :: Python :: 3.12
Classifier: Operating System :: OS Independent
Requires-Python: >=3.7
License-File: LICENSE
Requires-Dist: QtPy>=2.4.1
Provides-Extra: dev
Requires-Dist: pytest>=6.0; extra == "dev"
Requires-Dist: pytest-qt>=4.0; extra == "dev"
Requires-Dist: black; extra == "dev"
Requires-Dist: flake8; extra == "dev"
Requires-Dist: mypy; extra == "dev"
Provides-Extra: test
Requires-Dist: pytest>=6.0; extra == "test"
Requires-Dist: pytest-qt>=4.0; extra == "test"
Dynamic: author
Dynamic: home-page
Dynamic: license-file
Dynamic: requires-python
